ki_thermofluids/__init__.py
ki_thermofluids/flow.py
ki_thermofluids/humid_air.py
ki_thermofluids/mixture.py
ki_thermofluids/tests/__init__.py
ki_thermofluids/tests/test_flow.py
ki_thermofluids/tests/test_humid_air.py
ki_thermofluids/tests/test_thermo.py
ki_thermofluids/thermo.py
ki_thermofluids-0.1.0.dist-info/LICENSE
ki_thermofluids-0.1.0.dist-info/METADATA
ki_thermofluids-0.1.0.dist-info/WHEEL
ki_thermofluids-0.1.0.dist-info/RECORD
