Metadata-Version: 2.3
Name: ki_thermofluids
Version: 0.1.0
Summary: Thermofluid calculations. Home of ThermoState, FlowState, Orifice, and MinorLoss.
Author: Shiva Bernath
Author-email: shiva@karmanindustries.com
Requires-Python: >=3.11
Classifier: Programming Language :: Python :: 3
Classifier: Programming Language :: Python :: 3.11
Classifier: Programming Language :: Python :: 3.12
Classifier: Programming Language :: Python :: 3.13
Requires-Dist: coolprop (>=6.8.0,<7.0.0)
Requires-Dist: ki-util (>=0.2.0,<0.3.0)
Requires-Dist: numpy (>=2.3.1,<3.0.0)
Requires-Dist: pandas (>=2.3.1,<3.0.0)
Requires-Dist: pint (>=0.24.4,<0.25.0)
Requires-Dist: pytest (>=8.4.1,<9.0.0)
Requires-Dist: scipy (>=1.16.0,<2.0.0)
